ns_parental_controls
