Metadata-Version: 2.4
Name: ns_parental_controls
Version: 1.3.1
Summary: A simple interface to enable/disable your NS
Home-page: https://github.com/GrantGMiller/ns_parental_controls
Author: Grant miller
Author-email: grant@grant-miller.com
License: PSF
Project-URL: Source Code, https://github.com/GrantGMiller/ns_parental_controls
Keywords: grant miller ns parental controls
License-File: LICENSE
Requires-Dist: requests
Dynamic: author
Dynamic: author-email
Dynamic: description
Dynamic: home-page
Dynamic: keywords
Dynamic: license
Dynamic: license-file
Dynamic: project-url
Dynamic: requires-dist
Dynamic: summary
